adc_eval/__init__.py
adc_eval/filt.py
adc_eval/signals.py
adc_eval/adcs/__init__.py
adc_eval/adcs/basic.py
adc_eval/adcs/sar.py
adc_eval/eval/calc.py
adc_eval/eval/simulate.py
adc_eval/eval/spectrum.py
python_adc_eval-0.4.0.dist-info/LICENSE
python_adc_eval-0.4.0.dist-info/METADATA
python_adc_eval-0.4.0.dist-info/WHEEL
python_adc_eval-0.4.0.dist-info/top_level.txt
python_adc_eval-0.4.0.dist-info/RECORD
