Metadata-Version: 2.2
Name: python-adc-eval
Version: 0.4.0
Summary: ADC Evaluation Library
Author-email: Kevin Fronczak <kfronczak@gmail.com>
License: MIT
Project-URL: Source Code, https://github.com/fronzbot/python-adc-eval
Project-URL: Bug Reports, https://github.com/fronzbot/python-adc-eval/issues
Keywords: adc,analog-to-digital,evaluation,eval,spectrum
Platform: any
Classifier: License :: OSI Approved :: MIT License
Classifier: Operating System :: OS Independent
Classifier: Programming Language :: Python :: 3.9
Classifier: Programming Language :: Python :: 3.10
Classifier: Programming Language :: Python :: 3.11
Classifier: Programming Language :: Python :: 3.12
Classifier: Topic :: Scientific/Engineering
Requires-Python: >=3.9.0
License-File: LICENSE
Requires-Dist: matplotlib==3.9.2
